congruent/__init__.py
congruent/pkg.py
congruent/actions/__init__.py
congruent/embeddings/__init__.py
congruent/events/__init__.py
congruent/llm/__init__.py
congruent/llm/exceptions.py
congruent/llm/hookspecs.py
congruent/llm/manager.py
congruent/llm/service.py
congruent/llm/providers/__init__.py
congruent/llm/providers/anthropic.py
congruent/llm/providers/openai.py
congruent/llm/providers/utils.py
congruent/plugins/__init__.py
congruent/schedulers/__init__.py
congruent/schemas/__init__.py
congruent/schemas/agent.py
congruent/schemas/completion.py
congruent/schemas/document.py
congruent/schemas/history.py
congruent/schemas/llm.py
congruent/schemas/message.py
congruent/schemas/tool.py
congruent/stores/__init__.py
congruent/utils/__init__.py
congruent/utils/tokens.py
examples/__init__.py
examples/anonymization.py
examples/async_simple.py
examples/citation_rag.py
examples/entity_resolution.py
examples/extract_iterative_knowledge_graph.py
examples/extract_knowledge_graph.py
examples/extracting_receipts.py
examples/extracting_structure_Data_from_md.py
examples/image_to_ad_copy.py
examples/pii.py
examples/query_planning.py
examples/response_format.py
examples/search_planning.py
examples/simple.py
examples/test_classification.py
examples/tools.py
examples/user_defined_bulk_calssification.py
examples/utils.py
congruent-0.0.9.dist-info/LICENSE
congruent-0.0.9.dist-info/METADATA
congruent-0.0.9.dist-info/WHEEL
congruent-0.0.9.dist-info/top_level.txt
congruent-0.0.9.dist-info/RECORD
